lbparticles/__about__.py
lbparticles/__init__.py
lbparticles/lbparticles.py
lbparticles/particle.py
lbparticles/potentials.py
lbparticles/precomputer.py
lbparticles/util.py
lbparticles-0.1.6.dist-info/METADATA
lbparticles-0.1.6.dist-info/WHEEL
lbparticles-0.1.6.dist-info/licenses/LICENSE.txt
lbparticles-0.1.6.dist-info/RECORD
