Metadata-Version: 2.3
Name: lbparticles
Version: 0.1.6
Project-URL: Documentation, https://github.com/lbparticles/lbparticles#readme
Project-URL: Issues, https://github.com/lbparticles/lbparticles/issues
Project-URL: Source, https://github.com/lbparticles/lbparticles
Author-email: John Forbes <john.forbes@canterbury.ac.nz>, Jack Patterson <jack.patterson@canterbury.ac.nz>, Angus Forrest <angus.forrest@canterbury.ac.nz>
License: MIT
Classifier: Development Status :: 4 - Beta
Classifier: Programming Language :: Python
Classifier: Programming Language :: Python :: 3.8
Classifier: Programming Language :: Python :: 3.9
Classifier: Programming Language :: Python :: 3.10
Classifier: Programming Language :: Python :: 3.11
Classifier: Programming Language :: Python :: 3.12
Classifier: Programming Language :: Python :: Implementation :: CPython
Classifier: Programming Language :: Python :: Implementation :: PyPy
Requires-Python: >=3.8
Requires-Dist: numpy>=1.26.2
Requires-Dist: scipy>=1.11.3
Provides-Extra: docs
Requires-Dist: ipython; extra == 'docs'
Requires-Dist: myst-nb; extra == 'docs'
Requires-Dist: pandoc; extra == 'docs'
Requires-Dist: sphinx-book-theme; extra == 'docs'
Requires-Dist: sphinx>=7.2.6; extra == 'docs'
Provides-Extra: test
Requires-Dist: pytest; extra == 'test'
